<package>
  <description brief="position_tracker">

     position_tracker

  </description>
  <author>Joshua Lurz</author>
  <license>BSD</license>
  <review status="unreviewed" notes=""/>
  <url>http://ros.org/wiki/position_tracker</url>
  <rosdep name="pcl" />
  <depend package="roscpp"/>
  <depend package="kalman"/>
  <depend package="geometry_msgs"/>
  <depend package="tf"/>
  <depend package="cmvision"/>
  <depend package="pcl_ros"/>
  <depend package="actionlib"/>
  <depend package="actionlib_msgs"/>
  <depend package="rospy"/>
  <depend package="roslib"/>
  <depend package="std_msgs"/>
  <depend package="pr2_controllers_msgs"/>
  <depend package="gazebo_msgs" />
  <depend package="image_geometry" />
  <depend package="opencv2"/>
  <depend package="cv_bridge"/>
</package>


